yuque_mcp/__init__.py
yuque_mcp/mcp_instance.py
yuque_mcp/server.py
yuque_mcp/tools/__init__.py
yuque_mcp/tools/create_yuque_doc_in_group.py
yuque_mcp/tools/create_yuque_group.py
yuque_mcp/tools/get_yuque_doc_detail.py
yuque_mcp/tools/get_yuque_doc_list.py
yuque_mcp/tools/get_yuque_repo_toc.py
yuque_mcp-0.1.0.dist-info/METADATA
yuque_mcp-0.1.0.dist-info/WHEEL
yuque_mcp-0.1.0.dist-info/entry_points.txt
yuque_mcp-0.1.0.dist-info/licenses/LICENSE
yuque_mcp-0.1.0.dist-info/RECORD
