Metadata-Version: 2.4
Name: yuque-mcp
Version: 0.1.0
Summary: A Model Context Protocol server for Yuque
Project-URL: Homepage, https://github.com/yourusername/yuque-mcp
Project-URL: Repository, https://github.com/yourusername/yuque-mcp
Project-URL: Issues, https://github.com/yourusername/yuque-mcp/issues
Author-email: Your Name <your.email@example.com>
License-Expression: MIT
License-File: LICENSE
Keywords: ai,mcp,model-context-protocol,yuque
Classifier: Development Status :: 3 - Alpha
Classifier: Intended Audience :: Developers
Classifier: License :: OSI Approved :: MIT License
Classifier: Operating System :: OS Independent
Classifier: Programming Language :: Python :: 3
Classifier: Programming Language :: Python :: 3.9
Classifier: Programming Language :: Python :: 3.10
Classifier: Programming Language :: Python :: 3.11
Classifier: Programming Language :: Python :: 3.12
Classifier: Programming Language :: Python :: 3.13
Classifier: Topic :: Software Development :: Libraries :: Python Modules
Requires-Python: >=3.9
Requires-Dist: fastmcp>=2.12.0
Requires-Dist: python-dotenv>=1.1.1
Requires-Dist: requests>=2.32.5
Requires-Dist: starlette>=0.47.3
